bongram/__init__.py
bongram/cli.py
bongram/core.py
bongram/templates/__init__.py
bongram/templates/booking/bot.py
bongram/templates/faq/bot.py
bongram/templates/feedback/bot.py
bongram/templates/filemanager/bot.py
bongram/templates/giveaway/bot.py
bongram/templates/moderator/bot.py
bongram/templates/newsletter/bot.py
bongram/templates/paymentsplitter/bot.py
bongram/templates/polling/bot.py
bongram/templates/quiz/bot.py
bongram/templates/referral/bot.py
bongram/templates/reminder/bot.py
bongram/templates/support/bot.py
bongram-0.1.1.dist-info/licenses/LICENSE
bongram-0.1.1.dist-info/METADATA
bongram-0.1.1.dist-info/WHEEL
bongram-0.1.1.dist-info/entry_points.txt
bongram-0.1.1.dist-info/top_level.txt
bongram-0.1.1.dist-info/RECORD
