Metadata-Version: 2.4
Name: bongram
Version: 0.1.1
Summary: Фреймворк для мгновенного создания Telegram-ботов на готовых шаблонах
Home-page: https://github.com/THWEDOKA/bongram
Author: Triazov Kirill
Author-email: contact@triazov.ru
Project-URL: Homepage, https://triazov.ru
Project-URL: Bug Reports, https://github.com/THWEDOKA/bongram/issues
Project-URL: Source, https://github.com/THWEDOKA/bongram
Classifier: Development Status :: 3 - Alpha
Classifier: Intended Audience :: Developers
Classifier: Topic :: Software Development :: Libraries :: Python Modules
Classifier: Programming Language :: Python :: 3
Classifier: Programming Language :: Python :: 3.8
Classifier: Programming Language :: Python :: 3.9
Classifier: Programming Language :: Python :: 3.10
Classifier: Programming Language :: Python :: 3.11
Classifier: License :: OSI Approved :: MIT License
Requires-Python: >=3.8
License-File: LICENSE
Requires-Dist: aiogram>=3.0.0
Dynamic: author
Dynamic: author-email
Dynamic: classifier
Dynamic: description
Dynamic: description-content-type
Dynamic: home-page
Dynamic: license-file
Dynamic: project-url
Dynamic: requires-dist
Dynamic: requires-python
Dynamic: summary
